{
  "dependencies": {
    "@bower_components/analytics": "./analytics",
    "@bower_components/angular-filter": "a8m/angular-filter#^0.5",
    "@bower_components/angular-strap": "mgcrea/angular-strap#*",
    "@bower_components/autosize-input": "https://github.com/yuanqing/autosize-input#cf73892e1b9ceff448c7ea5f4a41b4b8a6a3991c#*",
    "@bower_components/select2": "ivaynberg/select2#^4.0.3",
    "@bower_components/bootstrap-datepicker": "eternicode/bootstrap-datepicker#1.7",
    "@bower_components/angular-material": "angular/bower-material#^1.1.5",
    "@bower_components/resize-observer-polyfill": "que-etc/resize-observer-polyfill#^1.4.2",
    "@bower_components/ng-tags-input": "mbenford/ngTagsInput-bower#3.2.0",
    "@bower_components/eonasdan/bootstrap-datetimepicker": "eonasdan/bootstrap-datetimepicker#^4.17.47",
    "moment": "^2.22.1",
    "moment-timezone": "^0.5.23",
    "pouchdb": "^7.2.2",
    "pouchdb-find": "^7.2.2",
    "js-shortid": "^0.1.1",
    "font-awesome": "^4.6.3",
    "bootstrap-sass": "3.3.7",
    "react": "^17.0.2",
    "react-dom": "^17.0.2",
    "final-form": "^4.20.2",
    "react-final-form": "^6.5.3",
    "react-confirm-alert": "^2.7.0",
    "react-table": "^7.7.0",
    "react-router-breadcrumbs-hoc": "^4.1.0"
  },
  "engines": {
    "yarn": ">= 1.0.0"
  },
  "scripts": {
    "preinstall": "mkdir -p analytics && curl -o analytics/analytics.js https://www.google-analytics.com/analytics.js"
  },
  "overrides": {
    "@bower_components/angular-material": {
      "main": [
        "modules/js/virtualRepeat/virtualRepeat.js",
        "modules/js/virtualRepeat/virtualRepeat.css",
        "modules/js/showHide/showHide.js",
        "modules/js/core/core.js",
        "modules/js/core/core.css"
      ]
    },
    "@bower_components/select2": {
      "main": [
        "dist/js/select2.js"
      ]
    }
  }
}
